{
  "test_live_toggle": false,
  "test_live_mode": false,
  "magic_link": false,
  "production_access": false,
  "quick_start": false,
  "stripe_plus_paypal": false,
  "woocommerce": false,
  "open_sdk": false,
  "switch_merchant": false,
  "audit_trail": false,
  "system_metrics": false,
  "sample_data": false,
  "frm": false,
  "payout": false,
  "recon": false,
  "user_management": false,
  "test_processors": true,
  "feedback": false,
  "verify_connector": false,
  "mixpanel": false,
  "business_profile": false,
  "generate_report": false,
  "forgot_password": false
}
